cfservice/__init__.py
cfservice/errors.py
tools/__init__.py
cfshandler-0.0.7.dist-info/METADATA
cfshandler-0.0.7.dist-info/WHEEL
cfshandler-0.0.7.dist-info/top_level.txt
cfshandler-0.0.7.dist-info/RECORD
